hirefire_resource/__init__.py
hirefire_resource/configuration.py
hirefire_resource/errors.py
hirefire_resource/hirefire.py
hirefire_resource/macro/__init__.py
hirefire_resource/macro/celery.py
hirefire_resource/macro/rq.py
hirefire_resource/middleware/__init__.py
hirefire_resource/middleware/asgi/__init__.py
hirefire_resource/middleware/asgi/django.py
hirefire_resource/middleware/asgi/quart.py
hirefire_resource/middleware/asgi/starlette.py
hirefire_resource/middleware/wsgi/__init__.py
hirefire_resource/middleware/wsgi/django.py
hirefire_resource/middleware/wsgi/flask.py
hirefire_resource/version.py
hirefire_resource/web.py
hirefire_resource/worker.py
hirefire_resource-1.0.4.dist-info/METADATA
hirefire_resource-1.0.4.dist-info/WHEEL
hirefire_resource-1.0.4.dist-info/licenses/LICENSE
hirefire_resource-1.0.4.dist-info/RECORD
