Metadata-Version: 2.4
Name: hirefire-resource
Version: 1.0.4
Summary: HireFire integration library for Python applications
License: MIT
License-File: LICENSE
Keywords: hirefire,heroku,autoscale,autoscaling,autoscaler,web,worker,dyno
Author: Michael van Rooijen
Author-email: support@hirefire.io
Requires-Python: >=3.9,<4.0
Classifier: Intended Audience :: Developers
Classifier: License :: OSI Approved :: MIT License
Classifier: Operating System :: OS Independent
Classifier: Programming Language :: Python :: 3
Classifier: Programming Language :: Python :: 3.9
Classifier: Programming Language :: Python :: 3.10
Classifier: Programming Language :: Python :: 3.11
Classifier: Programming Language :: Python :: 3.12
Classifier: Programming Language :: Python :: 3.13
Classifier: Programming Language :: Python :: 3.14
Project-URL: Homepage, https://hirefire.io
Project-URL: Repository, https://github.com/hirefire/hirefire-resource-python
